{"cameraMode":{"drawMode":0,"name":"Shaded","section":"Shading Mode"},"sceneLighting":true,"audioPlay":false,"sceneViewState":{"m_AlwaysRefresh":false,"showFog":true,"showSkybox":true,"showFlares":true,"showImageEffects":true,"showParticleSystems":true,"showVisualEffectGraphs":true,"m_FxEnabled":true},"in2DMode":false,"pivot":{"x":467.9024658203125,"y":0.7993295192718506,"z":48.673702239990237},"rotation":{"x":0.2271992415189743,"y":-0.4324268102645874,"z":0.11355945467948914,"w":0.865166425704956},"size":2.3989248275756838,"orthographic":false}